ewah_bool_utils/__init__.py
ewah_bool_utils/_testing.abi3.so
ewah_bool_utils/_testing.pyx
ewah_bool_utils/ewah_bool_array.pxd
ewah_bool_utils/ewah_bool_wrap.abi3.so
ewah_bool_utils/ewah_bool_wrap.pxd
ewah_bool_utils/ewah_bool_wrap.pyx
ewah_bool_utils/morton_utils.abi3.so
ewah_bool_utils/morton_utils.pxd
ewah_bool_utils/morton_utils.pyx
ewah_bool_utils/cpp/LICENSE
ewah_bool_utils/cpp/README
ewah_bool_utils/cpp/boolarray.h
ewah_bool_utils/cpp/ewah-inl.h
ewah_bool_utils/cpp/ewah.h
ewah_bool_utils/cpp/ewahutil.h
ewah_bool_utils/cpp/runninglengthword.h
ewah_bool_utils/tests/__init__.py
ewah_bool_utils/tests/test_ewah_bool_utils.py
ewah_bool_utils.libs/libgcc_s-0cd532bd.so.1
ewah_bool_utils.libs/libstdc++-5d72f927.so.6.0.33
ewah_bool_utils-1.3.0.dist-info/METADATA
ewah_bool_utils-1.3.0.dist-info/WHEEL
ewah_bool_utils-1.3.0.dist-info/top_level.txt
ewah_bool_utils-1.3.0.dist-info/RECORD
ewah_bool_utils-1.3.0.dist-info/licenses/LICENSE
